[{"id":"ce4d561.e027ea8","type":"tab","label":"Flow 1","disabled":false,"info":""},{"id":"32f300c3.703","type":"multipart-decoder","z":"ce4d561.e027ea8","name":"","ret":"bin","url":"http://192.168.1.38:8080/video","tls":"","delay":0,"maximum":1000000,"blockSize":1,"x":680,"y":800,"wires":[["c50936af.6c7638"]]},{"id":"c50936af.6c7638","type":"multipart-encoder","z":"ce4d561.e027ea8","name":"","statusCode":"","ignoreMessages":true,"outputOneNew":false,"outputIfSingle":false,"outputIfAll":false,"globalHeaders":{"Content-Type":"multipart/x-mixed-replace;boundary=--myboundary","Connection":"keep-alive","Expires":"Fri, 01 Jan 1990 00:00:00 GMT","Cache-Control":"no-cache, no-store, max-age=0, must-revalidate","Pragma":"no-cache"},"partHeaders":{"Content-Type":"image/jpeg"},"destination":"all","highWaterMark":16384,"x":900,"y":680,"wires":[[]]},{"id":"78af2e59.64ea","type":"inject","z":"ce4d561.e027ea8","name":"Ga aan!","topic":"","payload":"1","payloadType":"num","repeat":"","crontab":"","once":false,"onceDelay":"0","x":170,"y":800,"wires":[["542e152d.69e60c"]]},{"id":"542e152d.69e60c","type":"function","z":"ce4d561.e027ea8","name":"Id-Code voor ip-camera","func":"[{\"id\":\"7f2b6b5c.691b64\",\"type\":\"http in\",\"z\":\"15244fe6.9ae87\",\"name\":\"\",\"url\":\"/infinite\",\"method\":\"get\",\"upload\":false,\"swaggerDoc\":\"\",\"x\":570,\"y\":120,\"wires\":[[\"5b3e4039.df33b\"]]},{\"id\":\"5b3e4039.df33b\",\"type\":\"multipart-encoder\",\"z\":\"15244fe6.9ae87\",\"name\":\"\",\"statusCode\":\"\",\"ignoreHeaders\":false,\"ignoreMessages\":true,\"outputIfSingle\":true,\"outputIfAll\":true,\"globalHeaders\":{\"Content-Type\":\"multipart/x-mixed-replace;boundary=--myboundary\",\"Connection\":\"keep-alive\",\"Expires\":\"Fri, 01 Jan 1990 00:00:00 GMT\",\"Cache-Control\":\"no-cache, no-store, max-age=0, must-revalidate\",\"Pragma\":\"no-cache\"},\"partHeaders\":{\"Content-Type\":\"image/jpeg\"},\"destination\":\"all\",\"x\":781,\"y\":120,\"wires\":[[\"ca54ad09.d6904\"]]},{\"id\":\"fb72a642.df0eb8\",\"type\":\"http request\",\"z\":\"15244fe6.9ae87\",\"name\":\"Get image by url\",\"method\":\"GET\",\"ret\":\"bin\",\"url\":\"\",\"tls\":\"\",\"x\":560,\"y\":180,\"wires\":[[\"5b3e4039.df33b\"]]},{\"id\":\"f8b8895a.77a838\",\"type\":\"interval\",\"z\":\"15244fe6.9ae87\",\"name\":\"Every second\",\"interval\":\"1\",\"onstart\":false,\"msg\":\"ping\",\"showstatus\":false,\"unit\":\"seconds\",\"statusformat\":\"YYYY-MM-D HH:mm:ss\",\"x\":150,\"y\":180,\"wires\":[[\"59a9f54a.322d2c\"]]},{\"id\":\"59a9f54a.322d2c\",\"type\":\"function\",\"z\":\"15244fe6.9ae87\",\"name\":\"Next image url\",\"func\":\"var counter = global.get(\\\"image_counter\\\") || 0; \\ncounter++;\\nglobal.set(\\\"image_counter\\\",counter);\\n\\nmsg.url = 'https://dummyimage.com/400x200/fff/000&text=PNG+' + counter;\\n\\nreturn msg;\",\"outputs\":1,\"noerr\":0,\"x\":340,\"y\":180,\"wires\":[[\"fb72a642.df0eb8\"]]},{\"id\":\"3ffa9ebc.86a872\",\"type\":\"comment\",\"z\":\"15244fe6.9ae87\",\"name\":\"Stream to all clients\",\"info\":\"\",\"x\":170,\"y\":120,\"wires\":[]},{\"id\":\"ca54ad09.d6904\",\"type\":\"debug\",\"z\":\"15244fe6.9ae87\",\"name\":\"Encoder output\",\"active\":true,\"console\":\"false\",\"complete\":\"res\",\"x\":954,\"y\":120,\"wires\":[]}]\nreturn msg;","outputs":1,"noerr":0,"x":390,"y":800,"wires":[["32f300c3.703"]]},{"id":"ed463204.4f4c5","type":"http in","z":"ce4d561.e027ea8","name":"","url":"video","method":"get","upload":false,"swaggerDoc":"","x":700,"y":680,"wires":[["c50936af.6c7638"]]},{"id":"d43d51d1.d3c8d","type":"serial in","z":"ce4d561.e027ea8","name":"Arduino Input","serial":"b41c8a0.7273078","x":150,"y":440,"wires":[["e2484faf.9624a"]]},{"id":"e2484faf.9624a","type":"split","z":"ce4d561.e027ea8","name":"","splt":"\\n","spltType":"str","arraySplt":1,"arraySpltType":"len","stream":false,"addname":"","x":300,"y":440,"wires":[["7f28b51d.ddc9fc"]]},{"id":"35415f7d.a4ec1","type":"ui_gauge","z":"ce4d561.e027ea8","name":"","group":"b2e872.df4c279","order":0,"width":0,"height":0,"gtype":"gage","title":"Vochtigheid","label":"%","format":"{{value}}","min":0,"max":"100","colors":["#00b500","#e6e600","#ca3838"],"seg1":"","seg2":"","x":1290,"y":340,"wires":[]},{"id":"2d1b6d8d.ed67d2","type":"ui_gauge","z":"ce4d561.e027ea8","name":"","group":"b2e872.df4c279","order":1,"width":0,"height":0,"gtype":"gage","title":"Temperatuur","label":"*C","format":"{{value}}","min":0,"max":"40","colors":["#00b500","#e6e600","#ca3838"],"seg1":"","seg2":"","x":1290,"y":380,"wires":[]},{"id":"d620f19d.1f7da","type":"ui_gauge","z":"ce4d561.e027ea8","name":"","group":"b2e872.df4c279","order":2,"width":0,"height":0,"gtype":"gage","title":"Luchtkwaliteit","label":"PPM","format":"{{value}}","min":0,"max":"1000","colors":["#00b500","#e6e600","#ca3838"],"seg1":"","seg2":"","x":1300,"y":420,"wires":[]},{"id":"7a069f03.00f6d","type":"ui_gauge","z":"ce4d561.e027ea8","name":"","group":"b2e872.df4c279","order":3,"width":0,"height":0,"gtype":"gage","title":"Alcohol","label":"PPM","format":"{{value}}","min":0,"max":"1000","colors":["#00b500","#e6e600","#ca3838"],"seg1":"","seg2":"","x":1280,"y":460,"wires":[]},{"id":"8d414ef6.d8bb2","type":"debug","z":"ce4d561.e027ea8","name":"vochtigheid","active":true,"tosidebar":true,"console":false,"tostatus":false,"complete":"payload","targetType":"msg","x":1170,"y":20,"wires":[]},{"id":"7f28b51d.ddc9fc","type":"switch","z":"ce4d561.e027ea8","name":"","property":"payload","propertyType":"msg","rules":[{"t":"cont","v":"Vochtigheid","vt":"str"},{"t":"cont","v":"Temperatuur","vt":"str"},{"t":"cont","v":"Luchtkwaliteit","vt":"str"},{"t":"cont","v":"Alcohol","vt":"str"}],"checkall":"true","repair":false,"outputs":4,"x":420,"y":440,"wires":[["b69a092a.3f1c28"],["5dc8af20.4c387"],["46e70c9e.3b4894"],["16564a7a.c470e6"]]},{"id":"a0d9affb.224fd","type":"debug","z":"ce4d561.e027ea8","name":"lucht","active":true,"tosidebar":true,"console":false,"tostatus":false,"complete":"payload","targetType":"msg","x":1150,"y":100,"wires":[]},{"id":"64e74a7d.7c2474","type":"debug","z":"ce4d561.e027ea8","name":"temp","active":true,"tosidebar":true,"console":false,"tostatus":false,"complete":"payload","targetType":"msg","x":1150,"y":60,"wires":[]},{"id":"3be76000.77c99","type":"debug","z":"ce4d561.e027ea8","name":"alcohol","active":true,"tosidebar":true,"console":false,"tostatus":false,"complete":"payload","targetType":"msg","x":1160,"y":140,"wires":[]},{"id":"16564a7a.c470e6","type":"change","z":"ce4d561.e027ea8","name":"Identifier verwijderer [ALCO]","rules":[{"t":"change","p":"payload","pt":"msg","from":"Alcohol PPM:","fromt":"str","to":"","tot":"str"},{"t":"change","p":"payload","pt":"msg","from":" ","fromt":"str","to":"","tot":"str"}],"action":"","property":"","from":"","to":"","reg":false,"x":650,"y":460,"wires":[["7a069f03.00f6d","84f1ca2c.b8f778"]]},{"id":"46e70c9e.3b4894","type":"change","z":"ce4d561.e027ea8","name":"Identifier verwijderer [LUCHT]","rules":[{"t":"change","p":"payload","pt":"msg","from":"Luchtkwaliteit: ","fromt":"str","to":"","tot":"str"},{"t":"change","p":"payload","pt":"msg","from":"PPM","fromt":"str","to":"","tot":"str"},{"t":"change","p":"payload","pt":"msg","from":" ","fromt":"str","to":"","tot":"str"}],"action":"","property":"","from":"","to":"","reg":false,"x":660,"y":420,"wires":[["d620f19d.1f7da","c9214521.41d2c8"]]},{"id":"b69a092a.3f1c28","type":"change","z":"ce4d561.e027ea8","name":"Identifier verwijderer [VOCHT]","rules":[{"t":"change","p":"payload","pt":"msg","from":"Vochtigheid:","fromt":"str","to":"","tot":"str"},{"t":"change","p":"payload","pt":"msg","from":"%","fromt":"str","to":"","tot":"str"},{"t":"change","p":"payload","pt":"msg","from":" ","fromt":"str","to":"","tot":"str"}],"action":"","property":"","from":"","to":"","reg":false,"x":670,"y":340,"wires":[["35415f7d.a4ec1","8769d9a5.ec7de8"]]},{"id":"5dc8af20.4c387","type":"change","z":"ce4d561.e027ea8","name":"Identifier verwijderer [TEMP]","rules":[{"t":"change","p":"payload","pt":"msg","from":"Temperatuur: ","fromt":"str","to":"","tot":"str"},{"t":"change","p":"payload","pt":"msg","from":"*C","fromt":"str","to":"","tot":"str"},{"t":"change","p":"payload","pt":"msg","from":" ","fromt":"str","to":"","tot":"str"}],"action":"","property":"","from":"","to":"","reg":false,"x":660,"y":380,"wires":[["2d1b6d8d.ed67d2","5bce32ef.673adc"]]},{"id":"80ca9778.ad3898","type":"debug","z":"ce4d561.e027ea8","name":"debug","active":true,"tosidebar":true,"console":false,"tostatus":false,"complete":"payload","targetType":"msg","x":970,"y":20,"wires":[]},{"id":"8769d9a5.ec7de8","type":"influxdb out","z":"ce4d561.e027ea8","influxdb":"cb222c7f.20664","name":"","measurement":"Vocht","precision":"","retentionPolicy":"","x":1310,"y":600,"wires":[]},{"id":"5bce32ef.673adc","type":"influxdb out","z":"ce4d561.e027ea8","influxdb":"cb222c7f.20664","name":"","measurement":"Temp","precision":"","retentionPolicy":"","x":1310,"y":640,"wires":[]},{"id":"c9214521.41d2c8","type":"influxdb out","z":"ce4d561.e027ea8","influxdb":"cb222c7f.20664","name":"","measurement":"Lucht","precision":"","retentionPolicy":"","x":1310,"y":680,"wires":[]},{"id":"84f1ca2c.b8f778","type":"influxdb out","z":"ce4d561.e027ea8","influxdb":"cb222c7f.20664","name":"","measurement":"Alco","precision":"","retentionPolicy":"","x":1310,"y":720,"wires":[]},{"id":"b41c8a0.7273078","type":"serial-port","z":"","serialport":"COM4","serialbaud":"9600","databits":"8","parity":"none","stopbits":"1","waitfor":"","dtr":"none","rts":"none","cts":"none","dsr":"none","newline":"\\n","bin":"false","out":"char","addchar":"","responsetimeout":"10000"},{"id":"b2e872.df4c279","type":"ui_group","z":"","name":"Alcohol","tab":"f937da6f.0b75b8","disp":true,"width":"6","collapse":false},{"id":"cb222c7f.20664","type":"influxdb","z":"","hostname":"127.0.0.1","port":"8086","protocol":"http","database":"catchpoint","name":"","usetls":false,"tls":""},{"id":"f937da6f.0b75b8","type":"ui_tab","z":"","name":"Arduino","icon":"dashboard","disabled":false,"hidden":false}]